{
  "recentFiles": [
    {
      "basename": "W16_Monday_2023_04_17",
      "path": "cal/W16_Monday_2023_04_17.md"
    },
    {
      "basename": "Teamcenter",
      "path": "prj/slim/notes/Teamcenter.md"
    },
    {
      "basename": "Release dictionary",
      "path": "Release dictionary.md"
    },
    {
      "basename": "2023-W17",
      "path": "cal/2023-W17.md"
    },
    {
      "basename": "W15_Tuesday_2023_04_11",
      "path": "cal/W15_Tuesday_2023_04_11.md"
    },
    {
      "basename": "TDA clock stopping",
      "path": "prj/slim/notes/TDA clock stopping.md"
    },
    {
      "basename": "W13_Monday_2023_03_27",
      "path": "cal/W13_Monday_2023_03_27.md"
    },
    {
      "basename": "Hardware reviews",
      "path": "prj/slim/notes/Hardware reviews.md"
    },
    {
      "basename": "socalled system BOM",
      "path": "prj/slim/out/socalled system BOM.md"
    },
    {
      "basename": "A13147800   A13600800   A09641600 nonauto",
      "path": "prj/slim/A13147800   A13600800   A09641600 nonauto.md"
    },
    {
      "basename": "Calorie",
      "path": "nir/Calorie.md"
    },
    {
      "basename": "A13147800   A13600800   A09641600 nonauto",
      "path": "A13147800   A13600800   A09641600 nonauto.md"
    },
    {
      "basename": "Jira 665943 Re differences from C1.9 to C.3.1",
      "path": "Jira 665943 Re differences from C1.9 to C.3.1.md"
    },
    {
      "basename": "Changes",
      "path": "Changes.md"
    },
    {
      "basename": "PMO mtg minutes",
      "path": "PMO mtg minutes.md"
    },
    {
      "basename": "Interface review HW29 HW31",
      "path": "prj/slim/out/Interface review HW29 HW31.md"
    },
    {
      "basename": "Slim and regular BOM list",
      "path": "prj/slim/out/Slim and regular BOM list.md"
    },
    {
      "basename": "Z2 TI suggested I2C registers",
      "path": "prj/slim/notes/Z2 TI suggested I2C registers.md"
    },
    {
      "basename": "Z2 C1.92 Unit test HW",
      "path": "Z2 C1.92 Unit test HW.md"
    },
    {
      "basename": "TI communication",
      "path": "prj/slim/notes/TI communication.md"
    },
    {
      "basename": "W11_Tuesday_2022_03_15",
      "path": "cal/W11_Tuesday_2022_03_15.md"
    },
    {
      "basename": "Z2 investigation after TI",
      "path": "prj/slim/notes/Z2 investigation after TI.md"
    },
    {
      "basename": "Khicas Xcas",
      "path": "Khicas Xcas.md"
    },
    {
      "basename": "Flash corruption (Micron  ISSI)",
      "path": "Flash corruption (Micron  ISSI).md"
    },
    {
      "basename": "general what goes here",
      "path": "MOC/general what goes here.md"
    },
    {
      "basename": "SPI writing to TCAN",
      "path": "prj/slim/notes/SPI writing to TCAN.md"
    },
    {
      "basename": "Load switch unitary test",
      "path": "prj/C2/notes/Load switch unitary test.md"
    },
    {
      "basename": "Qisda BOM",
      "path": "prj/slim/Qisda BOM.md"
    },
    {
      "basename": "SLIM ECU Microstrains",
      "path": "prj/slim/SLIM ECU Microstrains.md"
    },
    {
      "basename": "metasystem",
      "path": "meta/metasystem.md"
    },
    {
      "basename": "Mail tracking",
      "path": "prj/other/Mail tracking.md"
    },
    {
      "basename": "Rounds in the chamber",
      "path": "prj/slim/notes/Rounds in the chamber.md"
    },
    {
      "basename": "PV Camera short test issue ADAEX-65726",
      "path": "prj/slim/notes/PV Camera short test issue ADAEX-65726.md"
    },
    {
      "basename": "Test matrix",
      "path": "Test matrix.md"
    },
    {
      "basename": "D1 BOM generation error (TRTBTRTS)",
      "path": "prj/slim/D1 BOM generation error (TRTBTRTS).md"
    },
    {
      "basename": "W12_Monday_2023_03_20",
      "path": "cal/W12_Monday_2023_03_20.md"
    },
    {
      "basename": "W11_Monday_2023_03_13",
      "path": "cal/W11_Monday_2023_03_13.md"
    },
    {
      "basename": "Z2 canvas",
      "path": "prj/slim/notes/Z2 canvas.canvas"
    },
    {
      "basename": "Altium release list Output job",
      "path": "ref/Altium release list Output job.md"
    },
    {
      "basename": "C1.92 Milestone 0",
      "path": "C1.92 Milestone 0.md"
    }
  ],
  "omittedPaths": [],
  "maxLength": null
}